setup.cfg
setup.py
xround.py
xround.egg-info/PKG-INFO
xround.egg-info/SOURCES.txt
xround.egg-info/dependency_links.txt
xround.egg-info/requires.txt
xround.egg-info/top_level.txt