Metadata-Version: 1.1
Name: xround
Version: 1.0
Summary: Rounded corners for X
Home-page: https://github.com/vulkd/xround
Author: vulkd
Author-email: vulkdmail@gmail.com
License: UNKNOWN
Download-URL: https://github.com/vulkd/xround/archive/1.0.tar.gz
Platform: UNKNOWN
